setup.py
daily_funcs/__init__.py
daily_funcs/infer_pt.py
daily_funcs/infer_vllm.py
daily_funcs/odps_utils.py
daily_funcs/process_data.py
daily_funcs.egg-info/PKG-INFO
daily_funcs.egg-info/SOURCES.txt
daily_funcs.egg-info/dependency_links.txt
daily_funcs.egg-info/requires.txt
daily_funcs.egg-info/top_level.txt